yqpro1/__init__.py
yqpro1/hello.py
yqpro1-0.1.0.dist-info/METADATA
yqpro1-0.1.0.dist-info/WHEEL
yqpro1-0.1.0.dist-info/top_level.txt
yqpro1-0.1.0.dist-info/RECORD
