Metadata-Version: 2.4
Name: yqpro1
Version: 0.1.0
Summary: yqpro1 pacakge here 
Requires-Python: >=3.9
